aiogram_creator/__init__.py
aiogram_creator/main.py
aiogram_creator/template/factory.py
aiogram_creator/template/main.py
aiogram_creator/template/requirements.txt
aiogram_creator/template/settings.py
aiogram_creator/template/settings.yaml
aiogram_creator/template/filters/__init__.py
aiogram_creator/template/filters/chat.py
aiogram_creator/template/filters/states.py
aiogram_creator/template/handlers/__init__.py
aiogram_creator/template/handlers/main/__init__.py
aiogram_creator/template/handlers/main/menu.py
aiogram_creator/template/interface/__init__.py
aiogram_creator/template/interface/member.py
aiogram_creator/template/keyboards/__init__.py
aiogram_creator/template/keyboards/for_index.py
aiogram_creator/template/middlewares/__init__.py
aiogram_creator/template/middlewares/user_db.py
aiogram_creator/template/services/__init__.py
aiogram_creator/template/services/database.py
aiogram_creator/template/services/yaml_reader.py
aiogram_creator-1.0.6.dist-info/METADATA
aiogram_creator-1.0.6.dist-info/WHEEL
aiogram_creator-1.0.6.dist-info/entry_points.txt
aiogram_creator-1.0.6.dist-info/top_level.txt
aiogram_creator-1.0.6.dist-info/RECORD
